Workbook

Sheet DataSource
A1: Segment | B1: Country | C1: Product | D1: ID | E1: Discount Band | F1: Units Sold | G1: Manufacturing Price | H1: Sale Price | I1: Gross Sales | J1: Discounts | K1: Sales | L1: COGS | M1: Profit | N1: Date | O1: Month Number | P1: Month Name | Q1: Year
A2: Government | B2: Canada | C2: Carretera | D2: =CONCATENATE(financials[[#This Row],[Segment]],",",financials[[#This Row],[Country]],",",financials[[#This Row],[Product]]) -> Government,Canada,Carretera | E2: None | F2: =RANDBETWEEN(10,1000) -> 828 | G2: =VLOOKUP(financials[[#This Row],[ID]],Prices!D:F,2,FALSE) -> 20 | H2: =VLOOKUP(financials[[#This Row],[ID]],Prices!D:F,3,FALSE) -> 29 | I2: =financials[[#This Row],[Units Sold]]*financials[[#This Row],[Sale Price]] -> 24012 | J2: =IF( financials[[#This Row],[Gross Sales]] < 1000, financials[[#This Row],[Gross Sales]] * 0.01, IF( financials[[#This Row],[Gross Sales]] > 1000, financials[[#This Row],[Gross Sales]] * 0.05, IF( financials[[#This Row],[Gross Sales]] > 10000, financials[[#This Row],[Gross Sales]] * 0.1, IF( financials[[#This Row],[Gross Sales]] > 3000, financials[[#This Row],[Gross Sales]] * 0.15 ) ) ) ) -> 1200.6 | K2: =financials[[#This Row],[Gross Sales]]-financials[[#This Row],[Discounts]] -> 22811.4 | L2: =financials[[#This Row],[Units Sold]]*financials[[#This Row],[Manufacturing Price]] -> 16560 | M2: =financials[[#This Row],[Sales]]-financials[[#This Row],[COGS]] -> 6251.4 | N2: =TODAY()-RANDBETWEEN(1,732) -> 45097 | O2: =MONTH(financials[[#This Row],[Date]]) -> 6 | P2: =TEXT(financials[[#This Row],[Date]],"MMM") -> Jun | Q2: =YEAR(financials[[#This Row],[Date]]) -> 2023
A3: Government | B3: Germany | C3: Carretera | D3: =CONCATENATE(financials[[#This Row],[Segment]],",",financials[[#This Row],[Country]],",",financials[[#This Row],[Product]]) -> Government,Germany,Carretera | E3: None | F3: =RANDBETWEEN(10,1000) -> 368 | G3: =VLOOKUP(financials[[#This Row],[ID]],Prices!D:F,2,FALSE) -> 13 | H3: =VLOOKUP(financials[[#This Row],[ID]],Prices!D:F,3,FALSE) -> 22 | I3: =financials[[#This Row],[Units Sold]]*financials[[#This Row],[Sale Price]] -> 8096 | J3: =IF( financials[[#This Row],[Gross Sales]] < 1000, financials[[#This Row],[Gross Sales]] * 0.01, IF( financials[[#This Row],[Gross Sales]] > 1000, financials[[#This Row],[Gross Sales]] * 0.05, IF( financials[[#This Row],[Gross Sales]] > 10000, financials[[#This Row],[Gross Sales]] * 0.1, IF( financials[[#This Row],[Gross Sales]] > 3000, financials[[#This Row],[Gross Sales]] * 0.15 ) ) ) ) -> 404.8 | K3: =financials[[#This Row],[Gross Sales]]-financials[[#This Row],[Discounts]] -> 7691.2 | L3: =financials[[#This Row],[Units Sold]]*financials[[#This Row],[Manufacturing Price]] -> 4784 | M3: =financials[[#This Row],[Sales]]-financials[[#This Row],[COGS]] -> 2907.2 | N3: =TODAY()-RANDBETWEEN(1,732) -> 45758 | O3: =MONTH(financials[[#This Row],[Date]]) -> 4 | P3: =TEXT(financials[[#This Row],[Date]],"MMM") -> Apr | Q3: =YEAR(financials[[#This Row],[Date]]) -> 2025
A4: Midmarket | B4: France | C4: Carretera | D4: =CONCATENATE(financials[[#This Row],[Segment]],",",financials[[#This Row],[Country]],",",financials[[#This Row],[Product]]) -> Midmarket,France,Carretera | E4: None | F4: =RANDBETWEEN(10,1000) -> 20 | G4: =VLOOKUP(financials[[#This Row],[ID]],Prices!D:F,2,FALSE) -> 19 | H4: =VLOOKUP(financials[[#This Row],[ID]],Prices!D:F,3,FALSE) -> 32 | I4: =financials[[#This Row],[Units Sold]]*financials[[#This Row],[Sale Price]] -> 640 | J4: =IF( financials[[#This Row],[Gross Sales]] < 1000, financials[[#This Row],[Gross Sales]] * 0.01, IF( financials[[#This Row],[Gross Sales]] > 1000, financials[[#This Row],[Gross Sales]] * 0.05, IF( financials[[#This Row],[Gross Sales]] > 10000, financials[[#This Row],[Gross Sales]] * 0.1, IF( financials[[#This Row],[Gross Sales]] > 3000, financials[[#This Row],[Gross Sales]] * 0.15 ) ) ) ) -> 6.4 | K4: =financials[[#This Row],[Gross Sales]]-financials[[#This Row],[Discounts]] -> 633.6 | L4: =financials[[#This Row],[Units Sold]]*financials[[#This Row],[Manufacturing Price]] -> 380 | M4: =financials[[#This Row],[Sales]]-financials[[#This Row],[COGS]] -> 253.6 | N4: =TODAY()-RANDBETWEEN(1,732) -> 45486 | O4: =MONTH(financials[[#This Row],[Date]]) -> 7 | P4: =TEXT(financials[[#This Row],[Date]],"MMM") -> Jul | Q4: =YEAR(financials[[#This Row],[Date]]) -> 2024
A5: Midmarket | B5: Germany | C5: Carretera | D5: =CONCATENATE(financials[[#This Row],[Segment]],",",financials[[#This Row],[Country]],",",financials[[#This Row],[Product]]) -> Midmarket,Germany,Carretera | E5: None | F5: =RANDBETWEEN(10,1000) -> 216 | G5: =VLOOKUP(financials[[#This Row],[ID]],Prices!D:F,2,FALSE) -> 17 | H5: =VLOOKUP(financials[[#This Row],[ID]],Prices!D:F,3,FALSE) -> 28 | I5: =financials[[#This Row],[Units Sold]]*financials[[#This Row],[Sale Price]] -> 6048 | J5: =IF( financials[[#This Row],[Gross Sales]] < 1000, financials[[#This Row],[Gross Sales]] * 0.01, IF( financials[[#This Row],[Gross Sales]] > 1000, financials[[#This Row],[Gross Sales]] * 0.05, IF( financials[[#This Row],[Gross Sales]] > 10000, financials[[#This Row],[Gross Sales]] * 0.1, IF( financials[[#This Row],[Gross Sales]] > 3000, financials[[#This Row],[Gross Sales]] * 0.15 ) ) ) ) -> 302.4 | K5: =financials[[#This Row],[Gross Sales]]-financials[[#This Row],[Discounts]] -> 5745.6 | L5: =financials[[#This Row],[Units Sold]]*financials[[#This Row],[Manufacturing Price]] -> 3672 | M5: =financials[[#This Row],[Sales]]-financials[[#This Row],[COGS]] -> 2073.6 | N5: =TODAY()-RANDBETWEEN(1,732) -> 45678 | O5: =MONTH(financials[[#This Row],[Date]]) -> 1 | P5: =TEXT(financials[[#This Row],[Date]],"MMM") -> Jan | Q5: =YEAR(financials[[#This Row],[Date]]) -> 2025
A6: Midmarket | B6: Mexico | C6: Carretera | D6: =CONCATENATE(financials[[#This Row],[Segment]],",",financials[[#This Row],[Country]],",",financials[[#This Row],[Product]]) -> Midmarket,Mexico,Carretera | E6: None | F6: =RANDBETWEEN(10,1000) -> 511 | G6: =VLOOKUP(financials[[#This Row],[ID]],Prices!D:F,2,FALSE) -> 16 | H6: =VLOOKUP(financials[[#This Row],[ID]],Prices!D:F,3,FALSE) -> 21 | I6: =financials[[#This Row],[Units Sold]]*financials[[#This Row],[Sale Price]] -> 10731 | J6: =IF( financials[[#This Row],[Gross Sales]] < 1000, financials[[#This Row],[Gross Sales]] * 0.01, IF( financials[[#This Row],[Gross Sales]] > 1000, financials[[#This Row],[Gross Sales]] * 0.05, IF( financials[[#This Row],[Gross Sales]] > 10000, financials[[#This Row],[Gross Sales]] * 0.1, IF( financials[[#This Row],[Gross Sales]] > 3000, financials[[#This Row],[Gross Sales]] * 0.15 ) ) ) ) -> 536.55 | K6: =financials[[#This Row],[Gross Sales]]-financials[[#This Row],[Discounts]] -> 10194.45 | L6: =financials[[#This Row],[Units Sold]]*financials[[#This Row],[Manufacturing Price]] -> 8176 | M6: =financials[[#This Row],[Sales]]-financials[[#This Row],[COGS]] -> 2018.45 | N6: =TODAY()-RANDBETWEEN(1,732) -> 45633 | O6: =MONTH(financials[[#This Row],[Date]]) -> 12 | P6: =TEXT(financials[[#This Row],[Date]],"MMM") -> Dec | Q6: =YEAR(financials[[#This Row],[Date]]) -> 2024
A7: Government | B7: Germany | C7: Carretera | D7: =CONCATENATE(financials[[#This Row],[Segment]],",",financials[[#This Row],[Country]],",",financials[[#This Row],[Product]]) -> Government,Germany,Carretera | E7: None | F7: =RANDBETWEEN(10,1000) -> 73 | G7: =VLOOKUP(financials[[#This Row],[ID]],Prices!D:F,2,FALSE) -> 13 | H7: =VLOOKUP(financials[[#This Row],[ID]],Prices!D:F,3,FALSE) -> 22 | I7: =financials[[#This Row],[Units Sold]]*financials[[#This Row],[Sale Price]] -> 1606 | J7: =IF( financials[[#This Row],[Gross Sales]] < 1000, financials[[#This Row],[Gross Sales]] * 0.01, IF( financials[[#This Row],[Gross Sales]] > 1000, financials[[#This Row],[Gross Sales]] * 0.05, IF( financials[[#This Row],[Gross Sales]] > 10000, financials[[#This Row],[Gross Sales]] * 0.1, IF( financials[[#This Row],[Gross Sales]] > 3000, financials[[#This Row],[Gross Sales]] * 0.15 ) ) ) ) -> 80.3 | K7: =financials[[#This Row],[Gross Sales]]-financials[[#This Row],[Discounts]] -> 1525.7 | L7: =financials[[#This Row],[Units Sold]]*financials[[#This Row],[Manufacturing Price]] -> 949 | M7: =financials[[#This Row],[Sales]]-financials[[#This Row],[COGS]] -> 576.7 | N7: =TODAY()-RANDBETWEEN(1,732) -> 45123 | O7: =MONTH(financials[[#This Row],[Date]]) -> 7 | P7: =TEXT(financials[[#This Row],[Date]],"MMM") -> Jul | Q7: =YEAR(financials[[#This Row],[Date]]) -> 2023
A8: Midmarket | B8: Germany | C8: Montana | D8: =CONCATENATE(financials[[#This Row],[Segment]],",",financials[[#This Row],[Country]],",",financials[[#This Row],[Product]]) -> Midmarket,Germany,Montana | E8: None | F8: =RANDBETWEEN(10,1000) -> 121 | G8: =VLOOKUP(financials[[#This Row],[ID]],Prices!D:F,2,FALSE) -> 19 | H8: =VLOOKUP(financials[[#This Row],[ID]],Prices!D:F,3,FALSE) -> 34 | I8: =financials[[#This Row],[Units Sold]]*financials[[#This Row],[Sale Price]] -> 4114 | J8: =IF( financials[[#This Row],[Gross Sales]] < 1000, financials[[#This Row],[Gross Sales]] * 0.01, IF( financials[[#This Row],[Gross Sales]] > 1000, financials[[#This Row],[Gross Sales]] * 0.05, IF( financials[[#This Row],[Gross Sales]] > 10000, financials[[#This Row],[Gross Sales]] * 0.1, IF( financials[[#This Row],[Gross Sales]] > 3000, financials[[#This Row],[Gross Sales]] * 0.15 ) ) ) ) -> 205.7 | K8: =financials[[#This Row],[Gross Sales]]-financials[[#This Row],[Discounts]] -> 3908.3 | L8: =financials[[#This Row],[Units Sold]]*financials[[#This Row],[Manufacturing Price]] -> 2299 | M8: =financials[[#This Row],[Sales]]-financials[[#This Row],[COGS]] -> 1609.3 | N8: =TODAY()-RANDBETWEEN(1,732) -> 45578 | O8: =MONTH(financials[[#This Row],[Date]]) -> 10 | P8: =TEXT(financials[[#This Row],[Date]],"MMM") -> Oct | Q8: =YEAR(financials[[#This Row],[Date]]) -> 2024
A9: Channel Partners | B9: Canada | C9: Montana | D9: =CONCATENATE(financials[[#This Row],[Segment]],",",financials[[#This Row],[Country]],",",financials[[#This Row],[Product]]) -> Channel Partners,Canada,Montana | E9: None | F9: =RANDBETWEEN(10,1000) -> 25 | G9: =VLOOKUP(financials[[#This Row],[ID]],Prices!D:F,2,FALSE) -> 17 | H9: =VLOOKUP(financials[[#This Row],[ID]],Prices!D:F,3,FALSE) -> 26 | I9: =financials[[#This Row],[Units Sold]]*financials[[#This Row],[Sale Price]] -> 650 | J9: =IF( financials[[#This Row],[Gross Sales]] < 1000, financials[[#This Row],[Gross Sales]] * 0.01, IF( financials[[#This Row],[Gross Sales]] > 1000, financials[[#This Row],[Gross Sales]] * 0.05, IF( financials[[#This Row],[Gross Sales]] > 10000, financials[[#This Row],[Gross Sales]] * 0.1, IF( financials[[#This Row],[Gross Sales]] > 3000, financials[[#This Row],[Gross Sales]] * 0.15 ) ) ) ) -> 6.5 | K9: =financials[[#This Row],[Gross Sales]]-financials[[#This Row],[Discounts]] -> 643.5 | L9: =financials[[#This Row],[Units Sold]]*financials[[#This Row],[Manufacturing Price]] -> 425 | M9: =financials[[#This Row],[Sales]]-financials[[#This Row],[COGS]] -> 218.5 | N9: =TODAY()-RANDBETWEEN(1,732) -> 45316 | O9: =MONTH(financials[[#This Row],[Date]]) -> 1 | P9: =TEXT(financials[[#This Row],[Date]],"MMM") -> Jan | Q9: =YEAR(financials[[#This Row],[Date]]) -> 2024
A10: Government | B10: France | C10: Montana | D10: =CONCATENATE(financials[[#This Row],[Segment]],",",financials[[#This Row],[Country]],",",financials[[#This Row],[Product]]) -> Government,France,Montana | E10: None | F10: =RANDBETWEEN(10,1000) -> 639 | G10: =VLOOKUP(financials[[#This Row],[ID]],Prices!D:F,2,FALSE) -> 19 | H10: =VLOOKUP(financials[[#This Row],[ID]],Prices!D:F,3,FALSE) -> 22 | I10: =financials[[#This Row],[Units Sold]]*financials[[#This Row],[Sale Price]] -> 14058 | J10: =IF( financials[[#This Row],[Gross Sales]] < 1000, financials[[#This Row],[Gross Sales]] * 0.01, IF( financials[[#This Row],[Gross Sales]] > 1000, financials[[#This Row],[Gross Sales]] * 0.05, IF( financials[[#This Row],[Gross Sales]] > 10000, financials[[#This Row],[Gross Sales]] * 0.1, IF( financials[[#This Row],[Gross Sales]] > 3000, financials[[#This Row],[Gross Sales]] * 0.15 ) ) ) ) -> 702.9 | K10: =financials[[#This Row],[Gross Sales]]-financials[[#This Row],[Discounts]] -> 13355.1 | L10: =financials[[#This Row],[Units Sold]]*financials[[#This Row],[Manufacturing Price]] -> 12141 | M10: =financials[[#This Row],[Sales]]-financials[[#This Row],[COGS]] -> 1214.1 | N10: =TODAY()-RANDBETWEEN(1,732) -> 45586 | O10: =MONTH(financials[[#This Row],[Date]]) -> 10 | P10: =TEXT(financials[[#This Row],[Date]],"MMM") -> Oct | Q10: =YEAR(financials[[#This Row],[Date]]) -> 2024
A11: Channel Partners | B11: Germany | C11: Montana | D11: =CONCATENATE(financials[[#This Row],[Segment]],",",financials[[#This Row],[Country]],",",financials[[#This Row],[Product]]) -> Channel Partners,Germany,Montana | E11: None | F11: =RANDBETWEEN(10,1000) -> 188 | G11: =VLOOKUP(financials[[#This Row],[ID]],Prices!D:F,2,FALSE) -> 12 | H11: =VLOOKUP(financials[[#This Row],[ID]],Prices!D:F,3,FALSE) -> 33 | I11: =financials[[#This Row],[Units Sold]]*financials[[#This Row],[Sale Price]] -> 6204 | J11: =IF( financials[[#This Row],[Gross Sales]] < 1000, financials[[#This Row],[Gross Sales]] * 0.01, IF( financials[[#This Row],[Gross Sales]] > 1000, financials[[#This Row],[Gross Sales]] * 0.05, IF( financials[[#This Row],[Gross Sales]] > 10000, financials[[#This Row],[Gross Sales]] * 0.1, IF( financials[[#This Row],[Gross Sales]] > 3000, financials[[#This Row],[Gross Sales]] * 0.15 ) ) ) ) -> 310.2 | K11: =financials[[#This Row],[Gross Sales]]-financials[[#This Row],[Discounts]] -> 5893.8 | L11: =financials[[#This Row],[Units Sold]]*financials[[#This Row],[Manufacturing Price]] -> 2256 | M11: =financials[[#This Row],[Sales]]-financials[[#This Row],[COGS]] -> 3637.8 | N11: =TODAY()-RANDBETWEEN(1,732) -> 45479 | O11: =MONTH(financials[[#This Row],[Date]]) -> 7 | P11: =TEXT(financials[[#This Row],[Date]],"MMM") -> Jul | Q11: =YEAR(financials[[#This Row],[Date]]) -> 2024
A12: Midmarket | B12: Mexico | C12: Montana | D12: =CONCATENATE(financials[[#This Row],[Segment]],",",financials[[#This Row],[Country]],",",financials[[#This Row],[Product]]) -> Midmarket,Mexico,Montana | E12: None | F12: =RANDBETWEEN(10,1000) -> 711 | G12: =VLOOKUP(financials[[#This Row],[ID]],Prices!D:F,2,FALSE) -> 19 | H12: =VLOOKUP(financials[[#This Row],[ID]],Prices!D:F,3,FALSE) -> 17 | I12: =financials[[#This Row],[Units Sold]]*financials[[#This Row],[Sale Price]] -> 12087 | J12: =IF( financials[[#This Row],[Gross Sales]] < 1000, financials[[#This Row],[Gross Sales]] * 0.01, IF( financials[[#This Row],[Gross Sales]] > 1000, financials[[#This Row],[Gross Sales]] * 0.05, IF( financials[[#This Row],[Gross Sales]] > 10000, financials[[#This Row],[Gross Sales]] * 0.1, IF( financials[[#This Row],[Gross Sales]] > 3000, financials[[#This Row],[Gross Sales]] * 0.15 ) ) ) ) -> 604.35 | K12: =financials[[#This Row],[Gross Sales]]-financials[[#This Row],[Discounts]] -> 11482.65 | L12: =financials[[#This Row],[Units Sold]]*financials[[#This Row],[Manufacturing Price]] -> 13509 | M12: =financials[[#This Row],[Sales]]-financials[[#This Row],[COGS]] -> -2026.35 | N12: =TODAY()-RANDBETWEEN(1,732) -> 45242 | O12: =MONTH(financials[[#This Row],[Date]]) -> 11 | P12: =TEXT(financials[[#This Row],[Date]],"MMM") -> Nov | Q12: =YEAR(financials[[#This Row],[Date]]) -> 2023
A13: Enterprise | B13: Canada | C13: Montana | D13: =CONCATENATE(financials[[#This Row],[Segment]],",",financials[[#This Row],[Country]],",",financials[[#This Row],[Product]]) -> Enterprise,Canada,Montana | E13: None | F13: =RANDBETWEEN(10,1000) -> 902 | G13: =VLOOKUP(financials[[#This Row],[ID]],Prices!D:F,2,FALSE) -> 13 | H13: =VLOOKUP(financials[[#This Row],[ID]],Prices!D:F,3,FALSE) -> 23 | I13: =financials[[#This Row],[Units Sold]]*financials[[#This Row],[Sale Price]] -> 20746 | J13: =IF( financials[[#This Row],[Gross Sales]] < 1000, financials[[#This Row],[Gross Sales]] * 0.01, IF( financials[[#This Row],[Gross Sales]] > 1000, financials[[#This Row],[Gross Sales]] * 0.05, IF( financials[[#This Row],[Gross Sales]] > 10000, financials[[#This Row],[Gross Sales]] * 0.1, IF( financials[[#This Row],[Gross Sales]] > 3000, financials[[#This Row],[Gross Sales]] * 0.15 ) ) ) ) -> 1037.3 | K13: =financials[[#This Row],[Gross Sales]]-financials[[#This Row],[Discounts]] -> 19708.7 | L13: =financials[[#This Row],[Units Sold]]*financials[[#This Row],[Manufacturing Price]] -> 11726 | M13: =financials[[#This Row],[Sales]]-financials[[#This Row],[COGS]] -> 7982.7 | N13: =TODAY()-RANDBETWEEN(1,732) -> 45031 | O13: =MONTH(financials[[#This Row],[Date]]) -> 4 | P13: =TEXT(financials[[#This Row],[Date]],"MMM") -> Apr | Q13: =YEAR(financials[[#This Row],[Date]]) -> 2023
... A1401: Channel Partners | B1401: USA | C1401: VTT | D1401: =CONCATENATE(financials[[#This Row],[Segment]],",",financials[[#This Row],[Country]],",",financials[[#This Row],[Product]]) -> Channel Partners,USA,VTT | E1401: High | F1401: =RANDBETWEEN(10,1000) -> 798 | G1401: =VLOOKUP(financials[[#This Row],[ID]],Prices!D:F,2,FALSE) -> 20 | H1401: =VLOOKUP(financials[[#This Row],[ID]],Prices!D:F,3,FALSE) -> 38 | I1401: =financials[[#This Row],[Units Sold]]*financials[[#This Row],[Sale Price]] -> 30324 | J1401: =IF( financials[[#This Row],[Gross Sales]] < 1000, financials[[#This Row],[Gross Sales]] * 0.01, IF( financials[[#This Row],[Gross Sales]] > 1000, financials[[#This Row],[Gross Sales]] * 0.05, IF( financials[[#This Row],[Gross Sales]] > 10000, financials[[#This Row],[Gross Sales]] * 0.1, IF( financials[[#This Row],[Gross Sales]] > 3000, financials[[#This Row],[Gross Sales]] * 0.15 ) ) ) ) -> 1516.2 | K1401: =financials[[#This Row],[Gross Sales]]-financials[[#This Row],[Discounts]] -> 28807.8 | L1401: =financials[[#This Row],[Units Sold]]*financials[[#This Row],[Manufacturing Price]] -> 15960 | M1401: =financials[[#This Row],[Sales]]-financials[[#This Row],[COGS]] -> 12847.8 | N1401: =TODAY()-RANDBETWEEN(1,732) -> 45328 | O1401: =MONTH(financials[[#This Row],[Date]]) -> 2 | P1401: =TEXT(financials[[#This Row],[Date]],"MMM") -> Feb | Q1401: =YEAR(financials[[#This Row],[Date]]) -> 2024

Sheet Prices
A1: Segment | B1: Country | C1: Product | D1: ID | E1: Manufacturing Price | F1: Sale Price
A2: Government | B2: Canada | C2: Carretera | D2: =CONCATENATE(A2,",",B2,",",C2) -> Government,Canada,Carretera | E2: =RANDBETWEEN(10,20) -> 20 | F2: =RANDBETWEEN(16,38) -> 29
A3: Government | B3: Germany | C3: Carretera | D3: =CONCATENATE(A3,",",B3,",",C3) -> Government,Germany,Carretera | E3: =RANDBETWEEN(10,20) -> 13 | F3: =RANDBETWEEN(16,38) -> 22
A4: Midmarket | B4: France | C4: Carretera | D4: =CONCATENATE(A4,",",B4,",",C4) -> Midmarket,France,Carretera | E4: =RANDBETWEEN(10,20) -> 19 | F4: =RANDBETWEEN(16,38) -> 32
A5: Midmarket | B5: Germany | C5: Carretera | D5: =CONCATENATE(A5,",",B5,",",C5) -> Midmarket,Germany,Carretera | E5: =RANDBETWEEN(10,20) -> 17 | F5: =RANDBETWEEN(16,38) -> 28
A6: Midmarket | B6: Mexico | C6: Carretera | D6: =CONCATENATE(A6,",",B6,",",C6) -> Midmarket,Mexico,Carretera | E6: =RANDBETWEEN(10,20) -> 16 | F6: =RANDBETWEEN(16,38) -> 21
A7: Midmarket | B7: Germany | C7: Montana | D7: =CONCATENATE(A7,",",B7,",",C7) -> Midmarket,Germany,Montana | E7: =RANDBETWEEN(10,20) -> 19 | F7: =RANDBETWEEN(16,38) -> 34
A8: Channel Partners | B8: Canada | C8: Montana | D8: =CONCATENATE(A8,",",B8,",",C8) -> Channel Partners,Canada,Montana | E8: =RANDBETWEEN(10,20) -> 17 | F8: =RANDBETWEEN(16,38) -> 26
A9: Government | B9: France | C9: Montana | D9: =CONCATENATE(A9,",",B9,",",C9) -> Government,France,Montana | E9: =RANDBETWEEN(10,20) -> 19 | F9: =RANDBETWEEN(16,38) -> 22
A10: Channel Partners | B10: Germany | C10: Montana | D10: =CONCATENATE(A10,",",B10,",",C10) -> Channel Partners,Germany,Montana | E10: =RANDBETWEEN(10,20) -> 12 | F10: =RANDBETWEEN(16,38) -> 33
A11: Midmarket | B11: Mexico | C11: Montana | D11: =CONCATENATE(A11,",",B11,",",C11) -> Midmarket,Mexico,Montana | E11: =RANDBETWEEN(10,20) -> 19 | F11: =RANDBETWEEN(16,38) -> 17
A12: Enterprise | B12: Canada | C12: Montana | D12: =CONCATENATE(A12,",",B12,",",C12) -> Enterprise,Canada,Montana | E12: =RANDBETWEEN(10,20) -> 13 | F12: =RANDBETWEEN(16,38) -> 23
A13: Small Business | B13: Mexico | C13: Montana | D13: =CONCATENATE(A13,",",B13,",",C13) -> Small Business,Mexico,Montana | E13: =RANDBETWEEN(10,20) -> 20 | F13: =RANDBETWEEN(16,38) -> 37
... A151: Midmarket | B151: France | C151: Velo | D151: =CONCATENATE(A151,",",B151,",",C151) -> Midmarket,France,Velo | E151: =RANDBETWEEN(10,20) -> 12 | F151: =RANDBETWEEN(16,38) -> 28

Sheet ToCSV
A1: Segment | B1: Country | C1: Product | D1: ID | E1: Discount Band | F1: Units Sold | G1: Manufacturing Price | H1: Sale Price | I1: Gross Sales | J1: Discounts | K1: Sales | L1: COGS | M1: Profit | N1: Date | O1: Month Number | P1: Month Name | Q1: Year
A2: Government | B2: Canada | C2: Carretera | D2: Government,Canada,Carretera | E2: None | F2: 477 | G2: 12 | H2: 29 | I2: 13833 | J2: 691.65 | K2: 13141.35 | L2: 5724 | M2: 7417.35 | N2: 45150 | O2: 8 | P2: Aug | Q2: 2023
A3: Government | B3: Germany | C3: Carretera | D3: Government,Germany,Carretera | E3: None | F3: 418 | G3: 19 | H3: 19 | I3: 7942 | J3: 397.1 | K3: 7544.9 | L3: 7942 | M3: -397.1 | N3: 45694 | O3: 2 | P3: Feb | Q3: 2025
A4: Midmarket | B4: France | C4: Carretera | D4: Midmarket,France,Carretera | E4: None | F4: 520 | G4: 16 | H4: 22 | I4: 11440 | J4: 572 | K4: 10868 | L4: 8320 | M4: 2548 | N4: 45194 | O4: 9 | P4: Sep | Q4: 2023
A5: Midmarket | B5: Germany | C5: Carretera | D5: Midmarket,Germany,Carretera | E5: None | F5: 405 | G5: 14 | H5: 21 | I5: 8505 | J5: 425.25 | K5: 8079.75 | L5: 5670 | M5: 2409.75 | N5: 45343 | O5: 2 | P5: Feb | Q5: 2024
A6: Midmarket | B6: Mexico | C6: Carretera | D6: Midmarket,Mexico,Carretera | E6: None | F6: 97 | G6: 14 | H6: 20 | I6: 1940 | J6: 97 | K6: 1843 | L6: 1358 | M6: 485 | N6: 45042 | O6: 4 | P6: Apr | Q6: 2023
A7: Government | B7: Germany | C7: Carretera | D7: Government,Germany,Carretera | E7: None | F7: 818 | G7: 19 | H7: 19 | I7: 15542 | J7: 777.1 | K7: 14764.9 | L7: 15542 | M7: -777.1 | N7: 45690 | O7: 2 | P7: Feb | Q7: 2025
A8: Midmarket | B8: Germany | C8: Montana | D8: Midmarket,Germany,Montana | E8: None | F8: 806 | G8: 17 | H8: 16 | I8: 12896 | J8: 644.8 | K8: 12251.2 | L8: 13702 | M8: -1450.8 | N8: 45058 | O8: 5 | P8: May | Q8: 2023
A9: Channel Partners | B9: Canada | C9: Montana | D9: Channel Partners,Canada,Montana | E9: None | F9: 170 | G9: 13 | H9: 33 | I9: 5610 | J9: 280.5 | K9: 5329.5 | L9: 2210 | M9: 3119.5 | N9: 45103 | O9: 6 | P9: Jun | Q9: 2023
A10: Government | B10: France | C10: Montana | D10: Government,France,Montana | E10: None | F10: 692 | G10: 12 | H10: 35 | I10: 24220 | J10: 1211 | K10: 23009 | L10: 8304 | M10: 14705 | N10: 45663 | O10: 1 | P10: Jan | Q10: 2025
A11: Channel Partners | B11: Germany | C11: Montana | D11: Channel Partners,Germany,Montana | E11: None | F11: 711 | G11: 11 | H11: 28 | I11: 19908 | J11: 995.4 | K11: 18912.6 | L11: 7821 | M11: 11091.6 | N11: 45492 | O11: 7 | P11: Jul | Q11: 2024
A12: Midmarket | B12: Mexico | C12: Montana | D12: Midmarket,Mexico,Montana | E12: None | F12: 101 | G12: 16 | H12: 18 | I12: 1818 | J12: 90.9 | K12: 1727.1 | L12: 1616 | M12: 111.1 | N12: 45145 | O12: 8 | P12: Aug | Q12: 2023
A13: Enterprise | B13: Canada | C13: Montana | D13: Enterprise,Canada,Montana | E13: None | F13: 654 | G13: 11 | H13: 28 | I13: 18312 | J13: 915.6 | K13: 17396.4 | L13: 7194 | M13: 10202.4 | N13: 45529 | O13: 8 | P13: Aug | Q13: 2024
... A1401: Channel Partners | B1401: USA | C1401: VTT | D1401: Channel Partners,USA,VTT | E1401: High | F1401: 738 | G1401: 10 | H1401: 16 | I1401: 11808 | J1401: 590.4 | K1401: 11217.6 | L1401: 7380 | M1401: 3837.6 | N1401: 45080 | O1401: 6 | P1401: Jun | Q1401: 2023
